Metadata-Version: 2.1
Name: WellKnownHandler
Version: 0.0.1
Summary: Auxiliary Python3 library that allows for simple parsing and usage of an SSO server's "well-known" endpoints
Home-page: https://github.com/EOEPCA/well-known-handler
Author: EOEPCA
Author-email: angel.lozano@deimos-space.com
License: apache-2.0
Keywords: well,known,handler,EOEPCA,Well-known,User,Management
Platform: UNKNOWN
Classifier: Development Status :: 3 - Alpha
Classifier: Intended Audience :: Developers
Classifier: Topic :: Software Development :: Build Tools
Requires-Python: >=3.6
